setup.cfg
setup.py
netki/BaseObject.py
netki/Certificate.py
netki/Domain.py
netki/NetkiClient.py
netki/Partner.py
netki/Requestor.py
netki/WalletName.py
netki/__init__.py
netki/test_BaseObject.py
netki/test_Certificate.py
netki/test_Domain.py
netki/test_NetkiClient.py
netki/test_Partner.py
netki/test_Requestor.py
netki/test_WalletName.py
netki_partner_client.egg-info/PKG-INFO
netki_partner_client.egg-info/SOURCES.txt
netki_partner_client.egg-info/dependency_links.txt
netki_partner_client.egg-info/requires.txt
netki_partner_client.egg-info/top_level.txt