Metadata-Version: 1.0
Name: netki-partner-client
Version: 1.0.1
Summary: This Python module provides a client for Netki's (https://netki.com) Partner API.
Home-page: https://github.com/netkicorp/python-partner-api-client
Author: Netki Opensource
Author-email: opensource@netki.com
License: BSD
Keywords: netki,partner,certificate,walletname,wallet,name,bitcoin,blockchain,identity
Platform: UNKNOWN
